setup.py
oc_probability/Binomialdistribution.py
oc_probability/Gaussiandistribution.py
oc_probability/Generaldistribution.py
oc_probability/__init__.py
oc_probability.egg-info/PKG-INFO
oc_probability.egg-info/SOURCES.txt
oc_probability.egg-info/dependency_links.txt
oc_probability.egg-info/not-zip-safe
oc_probability.egg-info/top_level.txt