Metadata-Version: 1.0
Name: oc-probability
Version: 0.1
Summary: Gaussian and Binomial distributions
Home-page: UNKNOWN
Author: Otoniel Campos
Author-email: oc_campos16@hotmail.com
License: UNKNOWN
Platform: UNKNOWN
